requirements.txt
meddle/__init__.py
meddle/agent.py
meddle/interpreter.py
meddle/journal.py
meddle/journal2report.py
meddle/run.py
meddle/agents/__init__.py
meddle/agents/base_agent.py
meddle/agents/functional_agent.py
meddle/agents/hpo_agent.py
meddle/agents/proposal_agent.py
meddle/agents/tuning_agent.py
meddle/backend/__init__.py
meddle/backend/backend_anthropic.py
meddle/backend/backend_openai.py
meddle/backend/backend_openrouter.py
meddle/backend/utils.py
meddle/example_tasks/92-monai_q2d-retinamnist_224.py
meddle/knowledges/__init__.py
meddle/knowledges/utils.py
meddle/med_dl_tasks/clean_and_sort_csv.py
meddle/med_dl_tasks/clean_csv.py
meddle/med_dl_tasks/mco_wsi_os_baseline.py
meddle/med_dl_tasks/odir5k_2d_mlc/ODIR_evaluation.py
meddle/monai_rag/create_monai_rag_db.py
meddle/monai_rag/query_rag_db.py
meddle/utils/__init__.py
meddle/utils/config.py
meddle/utils/config.yaml
meddle/utils/data_preview.py
meddle/utils/metric.py
meddle/utils/resource_info.py
meddle/utils/response.py
meddle/utils/serialize.py
meddle/utils/timer.py
meddle/utils/tree_export.py
meddle/utils/viz_templates/template.html
meddle/utils/viz_templates/template.js
meddle-0.1.2.dist-info/licenses/LICENSE
meddle-0.1.2.dist-info/METADATA
meddle-0.1.2.dist-info/WHEEL
meddle-0.1.2.dist-info/entry_points.txt
meddle-0.1.2.dist-info/top_level.txt
meddle-0.1.2.dist-info/RECORD
