Metadata-Version: 2.4
Name: meddle
Version: 0.1.2
Summary: Agentic Medical Deep Learning Engineer
Author-email: Haoyu Wang <small_dark@sina.com>
Project-URL: Homepage, https://github.com/uni-medical/MedDLE
Classifier: Programming Language :: Python :: 3
Classifier: Operating System :: OS Independent
Classifier: Topic :: Scientific/Engineering :: Artificial Intelligence
Requires-Python: >=3.11
License-File: LICENSE
Requires-Dist: funcy==2.0
Requires-Dist: humanize==4.8.0
Requires-Dist: jsonschema==4.19.2
Requires-Dist: openai>=1.69.0
Requires-Dist: anthropic>=0.20.0
Requires-Dist: pytest==7.4.3
Requires-Dist: requests==2.31.0
Requires-Dist: rich==13.7.0
Requires-Dist: dataclasses_json>=0.6.4
Requires-Dist: omegaconf>=2.3.0
Requires-Dist: loguru==0.7.2
Requires-Dist: shutup>=0.2.0
Requires-Dist: coolname>=2.2.0
Requires-Dist: igraph>=0.11.3
Requires-Dist: genson>=1.2.0
Requires-Dist: lightgbm
Requires-Dist: matplotlib
Requires-Dist: seaborn
Requires-Dist: gensim
Requires-Dist: scikit-learn
Requires-Dist: opencv-python
Requires-Dist: scipy
Requires-Dist: biopython
Requires-Dist: imbalanced-learn
Requires-Dist: h5py
Requires-Dist: numba
Requires-Dist: arrow
Requires-Dist: markovify
Requires-Dist: imgaug
Requires-Dist: scikit-optimize
Requires-Dist: plotly
Requires-Dist: hyperopt
Requires-Dist: bayesian-optimization
Requires-Dist: imagecodecs
Requires-Dist: hmmlearn
Requires-Dist: bayespy==0.5.1
Requires-Dist: sklearn-pandas
Requires-Dist: tensorpack
Requires-Dist: sentencepiece
Requires-Dist: librosa
Requires-Dist: ipykernel
Requires-Dist: ipython
Requires-Dist: nbformat
Requires-Dist: kornia
Requires-Dist: Pillow
Requires-Dist: pyparsing
Requires-Dist: pytz
Requires-Dist: PyYAML
Requires-Dist: fastai
Requires-Dist: gym
Requires-Dist: optuna
Requires-Dist: transformers
Requires-Dist: datasets==2.1.0
Requires-Dist: torchmetrics
Requires-Dist: pytorch-lightning
Requires-Dist: sympy
Requires-Dist: timm
Requires-Dist: torchinfo
Requires-Dist: pdf2image
Requires-Dist: PyPDF
Requires-Dist: pyocr
Requires-Dist: pyarrow
Requires-Dist: xlrd
Requires-Dist: backoff
Requires-Dist: streamlit==1.40.2
Requires-Dist: python-dotenv
Requires-Dist: openpyxl
Requires-Dist: langchain
Requires-Dist: langchain-openai
Requires-Dist: langchain-community
Requires-Dist: beautifulsoup4
Requires-Dist: chromadb
Requires-Dist: SimpleITK
Requires-Dist: nibabel
Requires-Dist: html2text
Requires-Dist: tiktoken
Requires-Dist: autogluon
Requires-Dist: monai[all]==1.4.0
Requires-Dist: pydicom
Requires-Dist: lifelines
Dynamic: license-file
